orbithq_sdk/__init__.py
orbithq_sdk/client.py
orbithq_sdk/types.py
orbithq_sdk/wrappers/__init__.py
orbithq_sdk/wrappers/anthropic.py
orbithq_sdk/wrappers/openai.py
orbithq_sdk-0.1.2.dist-info/METADATA
orbithq_sdk-0.1.2.dist-info/WHEEL
orbithq_sdk-0.1.2.dist-info/top_level.txt
orbithq_sdk-0.1.2.dist-info/RECORD
