Metadata-Version: 2.4
Name: orbithq-sdk
Version: 0.1.2
Summary: Orbit - AI Cost Analytics SDK. Track, monitor, and optimize your AI spend.
Author-email: OrbitHQ <support@orbithq.ai>
License: MIT
Project-URL: Homepage, https://orbithq.ai
Project-URL: Documentation, https://orbithq.ai/docs
Project-URL: Repository, https://github.com/orbithq/sdk-python
Keywords: ai,llm,analytics,monitoring,openai,anthropic,cost-tracking,observability,orbit,orbithq
Classifier: Development Status :: 4 - Beta
Classifier: Intended Audience :: Developers
Classifier: License :: OSI Approved :: MIT License
Classifier: Programming Language :: Python :: 3
Classifier: Programming Language :: Python :: 3.8
Classifier: Programming Language :: Python :: 3.9
Classifier: Programming Language :: Python :: 3.10
Classifier: Programming Language :: Python :: 3.11
Classifier: Programming Language :: Python :: 3.12
Classifier: Topic :: Software Development :: Libraries :: Python Modules
Requires-Python: >=3.8
Requires-Dist: httpx>=0.24.0
Provides-Extra: openai
Requires-Dist: openai>=1.0.0; extra == "openai"
Provides-Extra: anthropic
Requires-Dist: anthropic>=0.18.0; extra == "anthropic"
Provides-Extra: all
Requires-Dist: openai>=1.0.0; extra == "all"
Requires-Dist: anthropic>=0.18.0; extra == "all"
Provides-Extra: dev
Requires-Dist: pytest>=7.0.0; extra == "dev"
Requires-Dist: pytest-asyncio>=0.21.0; extra == "dev"
Requires-Dist: mypy>=1.0.0; extra == "dev"
